texture/__init__.py
texture/game_master.py
texture/scenario.py
texture/util.py
texture-0.1.3.dist-info/DESCRIPTION.rst
texture-0.1.3.dist-info/METADATA
texture-0.1.3.dist-info/RECORD
texture-0.1.3.dist-info/WHEEL
texture-0.1.3.dist-info/metadata.json
texture-0.1.3.dist-info/pbr.json
texture-0.1.3.dist-info/top_level.txt
