Metadata-Version: 1.1
Name: texture
Version: 0.1.3
Summary: Micro-engine for creating text-based adventures
Home-page: https://github.com/rmed/texture
Author: Rafael Medina García
Author-email: rafamedgar@gmail.com
License: MIT
Keywords: texture adventure game text based old
Platform: UNKNOWN
Classifier: Development Status :: 4 - Beta
Classifier: Environment :: Console
Classifier: Intended Audience :: Developers
Classifier: Topic :: Games/Entertainment
Classifier: Topic :: Software Development
Classifier: Topic :: Utilities
Classifier: License :: OSI Approved :: MIT License
Classifier: Programming Language :: Python :: 2
Classifier: Programming Language :: Python :: 2.7
Classifier: Programming Language :: Python :: 3
Classifier: Programming Language :: Python :: 3.4
